elasticdeform-0.5.1.dist-info/RECORD
elasticdeform-0.5.1.dist-info/WHEEL
elasticdeform-0.5.1.dist-info/top_level.txt
elasticdeform-0.5.1.dist-info/LICENSE.txt
elasticdeform-0.5.1.dist-info/METADATA
elasticdeform/tf.py
elasticdeform/__init__.py
elasticdeform/torch.py
elasticdeform/_deform_grid.cpython-312-darwin.so
elasticdeform/deform_grid.py
