Metadata-Version: 2.1
Name: elasticdeform
Version: 0.5.1
Summary: Elastic deformations for N-D images.
Home-page: https://github.com/gvtulder/elasticdeform
Author: Gijs van Tulder
Author-email: gvtulder@gmail.com
License: BSD
Platform: UNKNOWN
Classifier: Programming Language :: Python :: 2
Classifier: Programming Language :: Python :: 3
Classifier: License :: OSI Approved :: BSD License
